node_buffer/__init__.py
node_buffer-0.4.0.dist-info/LICENSE
node_buffer-0.4.0.dist-info/METADATA
node_buffer-0.4.0.dist-info/WHEEL
node_buffer-0.4.0.dist-info/top_level.txt
node_buffer-0.4.0.dist-info/RECORD
